[
  {
    "image": "https://images.real-gifts.com/catalog/f/m/a/z9Xrl0Rk.jpg",
    "title": "edsfdfsdfdsfsdfsds"
  },
  {
    "image": "https://images.real-gifts.com/catalog/o/r/c/C5st9U7x.jpg",
    "title": "ggggggggggggggggggg"

  },
  {
    "image": "https://images.real-gifts.com/catalog/s/k/p/aIfaQAnQ.jpg",
    "title": "ffffffffffffffff"

  },
  {
    "image": "https://images.real-gifts.com/catalog/r/s/m/pUXfcS41.jpg",
    "title": "888888888888888888888"

  },
  {
    "image": "https://images.real-gifts.com/catalog/i/c/i/C9WphKY7.jpg",
    "title": "7777777777777777"

  },
  {
    "image": "https://images.real-gifts.com/catalog/x/r/l/qcrwHR2B.jpg",
    "title": "544444444444444444444"

  },
  {
    "image": "https://images.real-gifts.com/catalog/j/c/u/zPDdF84p.jpg",
    "title": "ed555555555555"

  },
  {
    "image": "https://images.real-gifts.com/catalog/c/h/j/8ytCYmgz.jpg",
    "title": "ed000000000"

  }
]
